asdk_plugin_data/__init__.py
asdk_plugin_data/api_registry.py
asdk_plugin_data/domain_apis_list.json
asdk_plugin_data/agraph/__init__.py
asdk_plugin_data/agraph/data/__init__.py
asdk_plugin_data/agraph/data/reference_data/__init__.py
asdk_plugin_data/agraph/data/reference_data/asset/__init__.py
asdk_plugin_data/agraph/data/reference_data/asset/asset_creation/__init__.py
asdk_plugin_data/agraph/data/reference_data/asset/asset_creation/v1/__init__.py
asdk_plugin_data/agraph/data/reference_data/asset/asset_creation/v1/SecurityCreationAPI/__init__.py
asdk_plugin_data/agraph/data/reference_data/asset/asset_creation/v1/SecurityCreationAPI/api_client.py
asdk_plugin_data/agraph/data/reference_data/asset/asset_creation/v1/SecurityCreationAPI/api_response.py
asdk_plugin_data/agraph/data/reference_data/asset/asset_creation/v1/SecurityCreationAPI/configuration.py
asdk_plugin_data/agraph/data/reference_data/asset/asset_creation/v1/SecurityCreationAPI/exceptions.py
asdk_plugin_data/agraph/data/reference_data/asset/asset_creation/v1/SecurityCreationAPI/rest.py
asdk_plugin_data/agraph/data/reference_data/asset/asset_creation/v1/SecurityCreationAPI/swagger.json
asdk_plugin_data/agraph/data/reference_data/asset/asset_creation/v1/SecurityCreationAPI/api/__init__.py
asdk_plugin_data/agraph/data/reference_data/asset/asset_creation/v1/SecurityCreationAPI/api/default_security_creation_api.py
asdk_plugin_data/agraph/data/reference_data/asset/asset_creation/v1/SecurityCreationAPI/models/__init__.py
asdk_plugin_data/agraph/data/reference_data/asset/asset_creation/v1/SecurityCreationAPI/models/any.py
asdk_plugin_data/agraph/data/reference_data/asset/asset_creation/v1/SecurityCreationAPI/models/assetasset_creationv1_arm_tba_security.py
asdk_plugin_data/agraph/data/reference_data/asset/asset_creation/v1/SecurityCreationAPI/models/assetasset_creationv1_cash_repo_security.py
asdk_plugin_data-2.0.0b2.dist-info/METADATA
asdk_plugin_data-2.0.0b2.dist-info/WHEEL
asdk_plugin_data-2.0.0b2.dist-info/top_level.txt
asdk_plugin_data-2.0.0b2.dist-info/RECORD
